.gitignore
LICENCE.txt
README.md
setup.cfg
setup.py
src/Exif/__init__.py
src/Exif/main.py
src/Exif_python.egg-info/PKG-INFO
src/Exif_python.egg-info/SOURCES.txt
src/Exif_python.egg-info/dependency_links.txt
src/Exif_python.egg-info/requires.txt
src/Exif_python.egg-info/top_level.txt